{
  "tasks": [
    {
      "id": "1767802980642",
      "text": "ai教育调研",
      "quadrant": "Q2",
      "completed": false,
      "created_at": "2026-01-08T00:23:00.642358"
    },
    {
      "id": "8fef8432-60e9-4aac-aa5d-f875bc2f8b99",
      "text": "小米创业思考",
      "quadrant": "Q2",
      "completed": false,
      "created_at": "2026-01-08T13:38:16.176052"
    },
    {
      "id": "0b968d4f-ea16-46e4-8966-c19a1079e197",
      "text": "述职报告ppt",
      "quadrant": "Q2",
      "completed": false,
      "created_at": "2026-01-08T13:40:42.623793"
    },
    {
      "id": "c18c8378-4cdd-494f-a741-501114b1d0a1",
      "text": "写周报",
      "quadrant": "Q1",
      "completed": false,
      "created_at": "2026-01-08T13:42:58.102589"
    },
    {
      "id": "4a4407fe-3236-462a-8438-396da30bfa63",
      "text": "梳理最近需要上线的list",
      "quadrant": "Q1",
      "completed": false,
      "created_at": "2026-01-08T13:43:22.361382"
    },
    {
      "id": "5885ed0b-8f5f-4547-96ed-ce5809c49872",
      "text": "做一个上线流程清单",
      "quadrant": "Q1",
      "completed": false,
      "created_at": "2026-01-08T13:43:36.030079"
    },
    {
      "id": "588355a6-58b3-490e-92f8-0d4d6c98c8fa",
      "text": "111",
      "quadrant": "Q1",
      "completed": false,
      "created_at": "2026-01-09T00:43:28.332217"
    },
    {
      "id": "b9d19c2a-ad7d-4531-a608-783300fbf7e4",
      "text": "1111",
      "quadrant": "Q1",
      "completed": false,
      "created_at": "2026-01-09T00:43:30.398602"
    },
    {
      "id": "faf5c455-df24-4253-9aa1-468b498b4620",
      "text": "12343",
      "quadrant": "Q1",
      "completed": false,
      "created_at": "2026-01-09T00:43:38.391268"
    },
    {
      "id": "9225ae3f-361c-4728-a031-dc93e0265899",
      "text": "12451234",
      "quadrant": "Q1",
      "completed": true,
      "created_at": "2026-01-09T00:43:41.450999"
    },
    {
      "id": "20be437c-361e-4d04-8cea-1697f82aa3b0",
      "text": "1234",
      "quadrant": "Q2",
      "completed": false,
      "created_at": "2026-01-09T00:54:51.842607"
    },
    {
      "id": "78b74da5-9b59-4ba5-afb7-e55b2283f6c7",
      "text": "1234",
      "quadrant": "Q2",
      "completed": false,
      "created_at": "2026-01-09T00:54:53.159815"
    },
    {
      "id": "b11e11bf-d580-43c4-8788-f752fdd83da3",
      "text": "1234",
      "quadrant": "Q2",
      "completed": false,
      "created_at": "2026-01-09T00:54:54.423942"
    },
    {
      "id": "78ca29e2-21ae-4942-b435-fbe7a53c1349",
      "text": "test",
      "quadrant": "Q4",
      "completed": false,
      "created_at": "2026-01-09T00:55:01.262105"
    },
    {
      "id": "fbdd86c3-304c-4a5c-b670-5834f9f95495",
      "text": "test",
      "quadrant": "Q4",
      "completed": false,
      "created_at": "2026-01-09T00:55:01.977994"
    },
    {
      "id": "36e68fa7-993a-410b-87e8-c927ce6dea76",
      "text": "set",
      "quadrant": "Q4",
      "completed": false,
      "created_at": "2026-01-09T00:55:03.015676"
    },
    {
      "id": "3c8fd52d-8925-43c0-bb98-5a626eb11d17",
      "text": "test",
      "quadrant": "Q4",
      "completed": false,
      "created_at": "2026-01-09T00:55:03.720441"
    },
    {
      "id": "5819dfcc-c644-45f2-8631-1a9e6b41568f",
      "text": "tes",
      "quadrant": "Q4",
      "completed": false,
      "created_at": "2026-01-09T00:55:04.451701"
    },
    {
      "id": "04efe2b5-80c7-489f-ab30-783590e87125",
      "text": "tes",
      "quadrant": "Q4",
      "completed": false,
      "created_at": "2026-01-09T00:55:05.367069"
    },
    {
      "id": "0eae9024-9a8f-40b0-8400-c0e6c8ed1a9c",
      "text": "test",
      "quadrant": "Q3",
      "completed": false,
      "created_at": "2026-01-09T00:55:18.241808"
    },
    {
      "id": "ac460fac-9f42-4c77-ad0c-8b1f44329030",
      "text": "set",
      "quadrant": "Q3",
      "completed": false,
      "created_at": "2026-01-09T00:55:19.104180"
    },
    {
      "id": "ad52e7d0-b66e-4c69-8286-df9799ae9679",
      "text": "tse",
      "quadrant": "Q3",
      "completed": false,
      "created_at": "2026-01-09T00:55:19.947355"
    }
  ]
}